fast_nig.cpython-313-darwin.so
fast_nig-0.1.2.dist-info/METADATA
fast_nig-0.1.2.dist-info/WHEEL
fast_nig-0.1.2.dist-info/top_level.txt
fast_nig-0.1.2.dist-info/RECORD
