Metadata-Version: 2.2
Name: fast_nig
Version: 0.1.2
Summary: NIG distribution with PPF approximations using cubic spline and pybind11
Author: YBaumann
Author-email: baumann@swissquant.com
Requires-Dist: pybind11>=2.6.0
Requires-Dist: numpy
Dynamic: author
Dynamic: author-email
Dynamic: requires-dist
Dynamic: summary
